scdata/__init__.py
scdata/_config/__init__.py
scdata/_config/config.py
scdata/device/__init__.py
scdata/device/device.py
scdata/device/plot/__init__.py
scdata/device/process/__init__.py
scdata/device/process/alphasense.py
scdata/device/process/baseline.py
scdata/device/process/error_codes.py
scdata/device/process/formulae.py
scdata/device/process/geoseries.py
scdata/device/process/params.py
scdata/device/process/regression.py
scdata/device/process/timeseries.py
scdata/io/__init__.py
scdata/io/device_api.py
scdata/io/device_file.py
scdata/io/model.py
scdata/models/__init__.py
scdata/models/models.py
scdata/test/__init__.py
scdata/test/test.py
scdata/test/checks/__init__.py
scdata/test/checks/checks.py
scdata/test/dispersion/__init__.py
scdata/test/dispersion/dispersion.py
scdata/test/export/__init__.py
scdata/test/export/to_file.py
scdata/test/export/templates/sc_template.html
scdata/test/plot/__init__.py
scdata/test/plot/box_plot.py
scdata/test/plot/heatmap_iplot.py
scdata/test/plot/heatmap_plot.py
scdata/test/plot/maps.py
scdata/test/plot/plot_tools.py
scdata/test/plot/scatter_dispersion_grid.py
scdata/test/plot/scatter_iplot.py
scdata/test/plot/scatter_plot.py
scdata/test/plot/target_diagram.py
scdata/test/plot/ts_dendrogram.py
scdata/test/plot/ts_dispersion_grid.py
scdata/test/plot/ts_dispersion_plot.py
scdata/test/plot/ts_dispersion_uplot.py
scdata/test/plot/ts_iplot.py
scdata/test/plot/ts_plot.py
scdata/test/plot/ts_scatter.py
scdata/test/plot/ts_uplot.py
scdata/test/tools/__init__.py
scdata/test/tools/combine.py
scdata/test/tools/history.py
scdata/test/tools/prepare.py
scdata/tools/__init__.py
scdata/tools/cleaning.py
scdata/tools/custom_logger.py
scdata/tools/date.py
scdata/tools/dictmerge.py
scdata/tools/find.py
scdata/tools/gets.py
scdata/tools/lazy.py
scdata/tools/location.py
scdata/tools/report.py
scdata/tools/series.py
scdata/tools/stats.py
scdata/tools/units.py
scdata/tools/url_check.py
scdata/tools/zenodo.py
scdata/tools/interim/example.csv
scdata-1.3.2.dist-info/licenses/LICENSE
scdata-1.3.2.dist-info/METADATA
scdata-1.3.2.dist-info/WHEEL
scdata-1.3.2.dist-info/top_level.txt
scdata-1.3.2.dist-info/RECORD
