Metadata-Version: 2.4
Name: scdata
Version: 1.3.2
Summary: Analysis of sensors and time series data
Home-page: https://github.com/fablabbcn/smartcitizen-data
Author: oscgonfer
License: GNU-GPL3.0
Project-URL: Documentation, https://docs.smartcitizen.me/
Project-URL: Source Code, https://github.com/fablabbcn/smartcitizen-data
Keywords: air,sensors,Smart Citizen
Classifier: Development Status :: 4 - Beta
Classifier: Intended Audience :: Education
Classifier: Intended Audience :: Science/Research
Classifier: Intended Audience :: Developers
Classifier: Topic :: Scientific/Engineering
Classifier: License :: OSI Approved :: GNU General Public License v3 (GPLv3)
Classifier: Programming Language :: Python :: 3
Requires-Python: >=3.9
License-File: LICENSE
Requires-Dist: branca~=0.4.0
Requires-Dist: Flask~=2.2.2
Requires-Dist: folium~=0.12.1
Requires-Dist: geopy~=1.21.0
Requires-Dist: Jinja2~=3.1.2
Requires-Dist: matplotlib
Requires-Dist: pandas~=2.2.2
Requires-Dist: pydantic
Requires-Dist: pytest
Requires-Dist: PyYAML~=6.0.1
Requires-Dist: requests
Requires-Dist: scipy
Requires-Dist: scikit-learn
Requires-Dist: seaborn
Requires-Dist: smartcitizen-connector
Requires-Dist: termcolor==1.1.0
Requires-Dist: tqdm~=4.50.2
Requires-Dist: timezonefinder~=6.1.9
Requires-Dist: urllib3
Requires-Dist: boto3
Requires-Dist: awswrangler
Dynamic: author
Dynamic: classifier
Dynamic: description
Dynamic: description-content-type
Dynamic: home-page
Dynamic: keywords
Dynamic: license
Dynamic: license-file
Dynamic: project-url
Dynamic: requires-dist
Dynamic: requires-python
Dynamic: summary
